databutton_logger/__init__.py
databutton_logger/logger.py
databutton_logger/middleware.py
databutton_logger-0.10.0.dist-info/METADATA
databutton_logger-0.10.0.dist-info/WHEEL
databutton_logger-0.10.0.dist-info/RECORD
