Metadata-Version: 2.1
Name: databutton-logger
Version: 0.10.0
Summary: Logger utilities for databutton
Author: Databutton
Requires-Python: >=3.9,<4.0
Classifier: Programming Language :: Python :: 3
Classifier: Programming Language :: Python :: 3.9
Classifier: Programming Language :: Python :: 3.10
Classifier: Programming Language :: Python :: 3.11
Requires-Dist: asgi-correlation-id (>=3.0.0,<5.0.0)
Requires-Dist: fastapi (>=0.65.0,<1.0)
Requires-Dist: httpx (>=0.18.0,<1.0.0)
Requires-Dist: loguru (>=0.5.0,<1.0.0)
